CHANGELOG.txt
LICENSE.txt
MANIFEST.in
README.txt
setup.py
calcuuu/__init__.py
calcuuuu.egg-info/PKG-INFO
calcuuuu.egg-info/SOURCES.txt
calcuuuu.egg-info/dependency_links.txt
calcuuuu.egg-info/top_level.txt
myenv/Lib/site-packages/typing_extensions.py
myenv/Lib/site-packages/_distutils_hack/__init__.py
myenv/Lib/site-packages/_distutils_hack/override.py
myenv/Lib/site-packages/backports/__init__.py
myenv/Lib/site-packages/backports.tarfile-1.2.0.dist-info/top_level.txt
myenv/Lib/site-packages/backports/tarfile/__init__.py
myenv/Lib/site-packages/backports/tarfile/__main__.py
myenv/Lib/site-packages/backports/tarfile/compat/__init__.py
myenv/Lib/site-packages/backports/tarfile/compat/py38.py
myenv/Lib/site-packages/certifi/__init__.py
myenv/Lib/site-packages/certifi/__main__.py
myenv/Lib/site-packages/certifi/core.py
myenv/Lib/site-packages/certifi-2025.7.9.dist-info/top_level.txt
myenv/Lib/site-packages/charset_normalizer/__init__.py
myenv/Lib/site-packages/charset_normalizer/__main__.py
myenv/Lib/site-packages/charset_normalizer/api.py
myenv/Lib/site-packages/charset_normalizer/cd.py
myenv/Lib/site-packages/charset_normalizer/constant.py
myenv/Lib/site-packages/charset_normalizer/legacy.py
myenv/Lib/site-packages/charset_normalizer/md.py
myenv/Lib/site-packages/charset_normalizer/models.py
myenv/Lib/site-packages/charset_normalizer/utils.py
myenv/Lib/site-packages/charset_normalizer/version.py
myenv/Lib/site-packages/charset_normalizer-3.4.2.dist-info/entry_points.txt
myenv/Lib/site-packages/charset_normalizer-3.4.2.dist-info/top_level.txt
myenv/Lib/site-packages/charset_normalizer/cli/__init__.py
myenv/Lib/site-packages/charset_normalizer/cli/__main__.py
myenv/Lib/site-packages/docutils/__init__.py
myenv/Lib/site-packages/docutils/__main__.py
myenv/Lib/site-packages/docutils/core.py
myenv/Lib/site-packages/docutils/examples.py
myenv/Lib/site-packages/docutils/frontend.py
myenv/Lib/site-packages/docutils/io.py
myenv/Lib/site-packages/docutils/nodes.py
myenv/Lib/site-packages/docutils/statemachine.py
myenv/Lib/site-packages/docutils-0.21.2.dist-info/COPYING.txt
myenv/Lib/site-packages/docutils-0.21.2.dist-info/entry_points.txt
myenv/Lib/site-packages/docutils/languages/__init__.py
myenv/Lib/site-packages/docutils/languages/af.py
myenv/Lib/site-packages/docutils/languages/ar.py
myenv/Lib/site-packages/docutils/languages/ca.py
myenv/Lib/site-packages/docutils/languages/cs.py
myenv/Lib/site-packages/docutils/languages/da.py
myenv/Lib/site-packages/docutils/languages/de.py
myenv/Lib/site-packages/id-1.5.0.dist-info/entry_points.txt
myenv/Lib/site-packages/importlib_metadata-8.7.0.dist-info/top_level.txt
myenv/Lib/site-packages/jaraco.classes-3.4.0.dist-info/top_level.txt
myenv/Lib/site-packages/jaraco.context-6.0.1.dist-info/top_level.txt
myenv/Lib/site-packages/jaraco_functools-4.2.1.dist-info/top_level.txt
myenv/Lib/site-packages/keyring-25.6.0.dist-info/entry_points.txt
myenv/Lib/site-packages/keyring-25.6.0.dist-info/top_level.txt
myenv/Lib/site-packages/markdown_it_py-3.0.0.dist-info/entry_points.txt
myenv/Lib/site-packages/pip-22.2.2.dist-info/LICENSE.txt
myenv/Lib/site-packages/pip-22.2.2.dist-info/entry_points.txt
myenv/Lib/site-packages/pip-22.2.2.dist-info/top_level.txt
myenv/Lib/site-packages/pygments-2.19.2.dist-info/entry_points.txt
myenv/Lib/site-packages/pywin32_ctypes-0.2.3.dist-info/LICENSE.txt
myenv/Lib/site-packages/pywin32_ctypes-0.2.3.dist-info/top_level.txt
myenv/Lib/site-packages/readme_renderer-44.0.dist-info/top_level.txt
myenv/Lib/site-packages/requests-2.32.4.dist-info/top_level.txt
myenv/Lib/site-packages/requests_toolbelt-1.0.0.dist-info/top_level.txt
myenv/Lib/site-packages/rfc3986-2.0.0.dist-info/top_level.txt
myenv/Lib/site-packages/setuptools-63.2.0.dist-info/entry_points.txt
myenv/Lib/site-packages/setuptools-63.2.0.dist-info/top_level.txt
myenv/Lib/site-packages/twine-6.1.0.dist-info/entry_points.txt
myenv/Lib/site-packages/twine-6.1.0.dist-info/top_level.txt
myenv/Lib/site-packages/urllib3-2.5.0.dist-info/licenses/LICENSE.txt
myenv/Lib/site-packages/zipp-3.23.0.dist-info/top_level.txt
